chess_program_generator/__init__.py
chess_program_generator/__main__.py
chess_program_generator/generator.py
chess_program_generator/py.typed
chess_program_generator-1.0.0.dist-info/LICENSE
chess_program_generator-1.0.0.dist-info/METADATA
chess_program_generator-1.0.0.dist-info/WHEEL
chess_program_generator-1.0.0.dist-info/entry_points.txt
chess_program_generator-1.0.0.dist-info/RECORD
